README.md
setup.py
olapp/__init__.py
olapp/settings.py
olapp/urls.py
olapp/wsgi.py
olapp/core/__init__.py
olapp/core/apps.py
olapp/core/forms.py
olapp/core/graphql.py
olapp/core/middleware.py
olapp/core/mutations.py
olapp/core/queries.py
olapp/core/sanitizers.py
olapp/core/utils.py
olapp/core/views.py
olapp/core/tests/__init__.py
olapp/core/tests/test_graphql.py
olapp/core/tests/test_sanitizers.py
olapp/formats/__init__.py
olapp/formats/cs/__init__.py
olapp/formats/cs/formats.py
openlobby_app.egg-info/PKG-INFO
openlobby_app.egg-info/SOURCES.txt
openlobby_app.egg-info/dependency_links.txt
openlobby_app.egg-info/top_level.txt